cbnumber/__init__.py
cbnumber/example.py
cbnumber-1.1.dist-info/METADATA
cbnumber-1.1.dist-info/WHEEL
cbnumber-1.1.dist-info/licenses/LICENSE
cbnumber-1.1.dist-info/RECORD
