Metadata-Version: 2.3
Name: cbnumber
Version: 1.1
Summary: A module representing numbers in arbitrary bases, extending the built-in `int` type.
Project-URL: Homepage, https://github.com/jmtalec/NumberBase
Project-URL: Issues, https://github.com/jmtalec/NumberBase/issues
Author-email: Jean Moïse Talec <jmtalec@gmail.com>
License-File: LICENSE
Classifier: License :: OSI Approved :: MIT License
Classifier: Operating System :: OS Independent
Classifier: Programming Language :: Python :: 3
Requires-Python: >=3.7
